<?xml version="1.0"?>
<opencv_storage>
<stage7>
  <maxWeakCount>53</maxWeakCount>
  <stageThreshold>-7.2283613681793213e-01</stageThreshold>
  <weakClassifiers>
    <_>
      <internalNodes>
        0 -1 1452 67108912 454036480 -1095084173 556795960 213392312
        -1409624351 67111384 1024</internalNodes>
      <leafValues>
        -1.0482528805732727e-01 6.3603532314300537e-01</leafValues></_>
    <_>
      <internalNodes>
        0 -1 2331 -1978522335 -1648703739 -1972477962 -1145212583
        -390069073 -4686370 -2135336193 -1501298640</internalNodes>
      <leafValues>
        -1.0978950560092926e-01 3.1141909956932068e-01</leafValues></_>
    <_>
      <internalNodes>
        0 -1 750 -276550731 -1688666 -2044136456 -4965723 263273180
        2145792367 -134410759 -1342962644</internalNodes>
      <leafValues>
        -1.6808231174945831e-01 2.7370944619178772e-01</leafValues></_>
    <_>
      <internalNodes>
        0 -1 2604 -628042432 -49415144 -8159237 -1321432528 1753810861
        -69557441 420051951 -2001417985</internalNodes>
      <leafValues>
        -1.8269376456737518e-01 2.3485833406448364e-01</leafValues></_>
    <_>
      <internalNodes>
        0 -1 1989 537536528 -1417258896 1900500211 -1235218388
        -1470618476 -540446431 -995602960 -1530892672</internalNodes>
      <leafValues>
        -3.0247172713279724e-01 1.0786401480436325e-01</leafValues></_>
    <_>
      <internalNodes>
        0 -1 3854 1346118016 -1819508468 -1861606565 2076720156 15146424
        1849053581 1749549306 217583664</internalNodes>
      <leafValues>
        -3.8547956943511963e-01 9.8414324223995209e-02</leafValues></_>
    <_>
      <internalNodes>
        0 -1 2059 1395689256 -93322118 -1915153488 957511120 1544162989
        504907903 984882412 828908962</internalNodes>
      <leafValues>
        -2.4216206371784210e-01 1.5725553035736084e-01</leafValues></_>
    <_>
      <internalNodes>
        0 -1 1414 -465433328 -2081679488 -1656568688 -110559248
        -88226259 136072212 1520711408 -1339015864</internalNodes>
      <leafValues>
        -2.4658150970935822e-01 1.5637329220771790e-01</leafValues></_>
    <_>
      <internalNodes>
        0 -1 3213 -429652667 1085283125 -1347622251 -71956512
        -1820838997 2025271159 -1511093783 -1599992815</internalNodes>
      <leafValues>
        -1.8471185863018036e-01 2.1430322527885437e-01</leafValues></_>
    <_>
      <internalNodes>
        0 -1 372 -608297565 -951682634 -2090787585 -7860244 310124061
        2124705645 230446772 -268490407</internalNodes>
      <leafValues>
        -1.5299600362777710e-01 2.4705043435096741e-01</leafValues></_>
    <_>
      <internalNodes>
        0 -1 1793 -632433852 508150629 -1408190467 -1612383300 522977317
        -1804000471 -1966380833 702267131</internalNodes>
      <leafValues>
        -1.8636819720268250e-01 2.1052123606204987e-01</leafValues></_>
    <_>
      <internalNodes>
        0 -1 3147 -2078669056 2118186816 1403970186 -75845903 1008995536
        -32225697 -755814223 -44175291</internalNodes>
      <leafValues>
        -1.9145497679710388e-01 2.0033235847949982e-01</leafValues></_>
    <_>
      <internalNodes>
        0 -1 1634 -487707386 1401725576 -1540936417 -799858792 186334493
        -546196498 -146315863 -777511628</internalNodes>
      <leafValues>
        -1.8457008898258209e-01 2.1231108903884888e-01</leafValues></_>
    <_>
      <internalNodes>
        0 -1 12 -1940444122 375933162 -813988716 -1450690446 1815581182
        1022037411 618205952 812266596</internalNodes>
      <leafValues>
        -2.7532964944839478e-01 1.4238856732845306e-01</leafValues></_>
    <_>
      <internalNodes>
        0 -1 1104 -1164138975 -337086041 2029360665 -72751965 -732242371
        -1439118228 1019477240 -89672709</internalNodes>
      <leafValues>
        -1.2359064072370529e-01 3.1590375304222107e-01</leafValues></_>
    <_>
      <internalNodes>
        0 -1 2978 -479209428 682393866 205476660 822132806 -1685301878
        967419073 1077208073 148260928</internalNodes>
      <leafValues>
        -2.6334244012832642e-01 1.4964705705642700e-01</leafValues></_>
    <_>
      <internalNodes>
        0 -1 3123 -856638351 -1296393936 -1981638734 -10113956 658131668
        1003757935 -121681990 -458279740</internalNodes>
      <leafValues>
        -1.5702140331268311e-01 2.5525534152984619e-01</leafValues></_>
    <_>
      <internalNodes>
        0 -1 20 -1044474400 781242756 -487169661 -1048591040 -1472444731
        1040205229 1577343580 -440302302</internalNodes>
      <leafValues>
        -2.1576070785522461e-01 1.8880343437194824e-01</leafValues></_>
    <_>
      <internalNodes>
        0 -1 1449 -1574300395 -341505973 -753608713 -655522428 583916212
        -1615978005 -1769075288 -2048376288</internalNodes>
      <leafValues>
        -1.9023105502128601e-01 2.0875513553619385e-01</leafValues></_>
    <_>
      <internalNodes>
        0 -1 3400 -260835845 1025948472 1832823634 535889328 972631005
        -331723475 469120937 -1143032131</internalNodes>
      <leafValues>
        -1.2139579653739929e-01 3.3931171894073486e-01</leafValues></_>
    <_>
      <internalNodes>
        0 -1 3204 -368652521 -617177415 -491344802 -1167320301
        -307016679 1879015421 2137190885 -2018810632</internalNodes>
      <leafValues>
        -1.5193723142147064e-01 2.7019745111465454e-01</leafValues></_>
    <_>
      <internalNodes>
        0 -1 2647 1212023415 -114043903 241509309 905574209 1028401221
        -1080530375 -1907094381 -827256239</internalNodes>
      <leafValues>
        -1.6597464680671692e-01 2.4803315103054047e-01</leafValues></_>
    <_>
      <internalNodes>
        0 -1 976 -1341673264 2071655202 -1592654167 -773145355 344234889
        -2122391303 -857482851 914138872</internalNodes>
      <leafValues>
        -1.9237507879734039e-01 2.1840026974678040e-01</leafValues></_>
    <_>
      <internalNodes>
        0 -1 3524 -355726025 -1086835463 -88119501 -68812947 -2047039841
        510494428 -622579804 -1695619608</internalNodes>
      <leafValues>
        -1.4168818295001984e-01 2.8926637768745422e-01</leafValues></_>
    <_>
      <internalNodes>
        0 -1 3438 -249542124 -1436265213 2127990866 -1771579324
        1078595021 1319603873 -1125248260 -508941984</internalNodes>
      <leafValues>
        -2.0115287601947784e-01 2.0718821883201599e-01</leafValues></_>
    <_>
      <internalNodes>
        0 -1 459 1815522796 1141925338 -58709329 -16743408 268969643
        -1139846907 -2024517396 -1654190059</internalNodes>
      <leafValues>
        -2.1595422923564911e-01 1.9493749737739563e-01</leafValues></_>
    <_>
      <internalNodes>
        0 -1 692 2014067460 238295842 -261582508 -1143954916 1170236577
        1033481623 349394924 211296292</internalNodes>
      <leafValues>
        -3.0880209803581238e-01 1.3170890510082245e-01</leafValues></_>
    <_>
      <internalNodes>
        0 -1 3900 -266297996 453391143 -273180311 366765594 -283604579
        -1629863945 988667580 -1907812027</internalNodes>
      <leafValues>
        -1.9201785326004028e-01 2.1237790584564209e-01</leafValues></_>
    <_>
      <internalNodes>
        0 -1 1114 -365231998 49432096 -1790701790 550174668 814549780
        73404453 -1043443456 1093786646</internalNodes>
      <leafValues>
        -5.3491997718811035e-01 8.2151368260383606e-02</leafValues></_>
    <_>
      <internalNodes>
        0 -1 3773 -2084649394 169527351 966136778 695824856 243497188
        -1914697250 990359948 552536603</internalNodes>
      <leafValues>
        -2.4003249406814575e-01 1.6958609223365784e-01</leafValues></_>
    <_>
      <internalNodes>
        0 -1 3693 -1583347680 709107008 538075485 836259984 76553352
        -1357950197 1714030816 1049648</internalNodes>
      <leafValues>
        -5.2903926372528076e-01 7.8071914613246918e-02</leafValues></_>
    <_>
      <internalNodes>
        0 -1 2079 -1402335768 -1866383112 -1254990572 -5153046 540002815
        168244285 -528025429 674111520</internalNodes>
      <leafValues>
        -2.4634231626987457e-01 1.6924366354942322e-01</leafValues></_>
    <_>
      <internalNodes>
        0 -1 1915 -462235845 389187868 143675975 -4107522 96726693
        1212321268 455107311 -1342331462</internalNodes>
      <leafValues>
        -1.3245493173599243e-01 3.2179298996925354e-01</leafValues></_>
    <_>
      <internalNodes>
        0 -1 3093 -1500346572 2074670281 -822529416 1000967314 993014437
        368532402 -2036153604 -1133947262</internalNodes>
      <leafValues>
        -1.8724717199802399e-01 2.2174558043479919e-01</leafValues></_>
    <_>
      <internalNodes>
        0 -1 3948 576769088 -2133149292 -17064904 -1300446423
        -1525442295 -451974811 1767258576 -2131395011</internalNodes>
      <leafValues>
        -2.5050082802772522e-01 1.6507634520530701e-01</leafValues></_>
    <_>
      <internalNodes>
        0 -1 1649 -674166873 1568335715 1943360409 1911324167
        -1283661907 -340491730 -1449816598 -542268917</internalNodes>
      <leafValues>
        -1.1177708953619003e-01 3.6909994482994080e-01</leafValues></_>
    <_>
      <internalNodes>
        0 -1 2495 -1395749724 -18686081 -2009594846 917411267
        -1741411813 -311664183 -1147636400 -1780461408</internalNodes>
      <leafValues>
        -2.2959475219249725e-01 1.8410220742225647e-01</leafValues></_>
    <_>
      <internalNodes>
        0 -1 3564 -1937620735 -1042061838 2134881424 -1850941581
        -571373122 -99705262 83755769 -1566949888</internalNodes>
      <leafValues>
        -1.8916453421115875e-01 2.1856935322284698e-01</leafValues></_>
    <_>
      <internalNodes>
        0 -1 2337 -564264829 -902971253 -1677047300 800817331
        -1059487415 665716760 -307705351 753214000</internalNodes>
      <leafValues>
        -2.0183369517326355e-01 2.0804372429847717e-01</leafValues></_>
    <_>
      <internalNodes>
        0 -1 652 1310974080 -1280317606 -424715556 -1925715472
        1729678745 1323989503 753076729 -670836682</internalNodes>
      <leafValues>
        -1.7575238645076752e-01 2.4953986704349518e-01</leafValues></_>
    <_>
      <internalNodes>
        0 -1 1026 -398960767 -492796410 1878786016 -51726060 1954269266
        -1673220635 2121312991 -135237338</internalNodes>
      <leafValues>
        -1.7858277261257172e-01 2.5025054812431335e-01</leafValues></_>
    <_>
      <internalNodes>
        0 -1 689 973387284 994400017 -1315212039 2119491367 55856824
        -2054437968 1088967099 254103355</internalNodes>
      <leafValues>
        -2.2007991373538971e-01 1.9145533442497253e-01</leafValues></_>
    <_>
      <internalNodes>
        0 -1 3312 1184899041 -1379528014 -1594241997 -711254528
        926908801 1779420483 -1399675713 -86059294</internalNodes>
      <leafValues>
        -1.5042300522327423e-01 2.8045633435249329e-01</leafValues></_>
    <_>
      <internalNodes>
        0 -1 920 -984908102 -1166872594 -779908028 1338708283 -852334394
        1934342430 579327898 1401786908</internalNodes>
      <leafValues>
        -2.1077899634838104e-01 2.0884171128273010e-01</leafValues></_>
    <_>
      <internalNodes>
        0 -1 1654 -1936022008 227325800 2098991472 -2011876592
        1829579840 245406742 -1601565195 -1008155547</internalNodes>
      <leafValues>
        -2.6047575473785400e-01 1.6398042440414429e-01</leafValues></_>
    <_>
      <internalNodes>
        0 -1 3157 -762422906 -479824573 -1170456547 -1490501442
        -1916491364 -15906002 -378968647 -1992169357</internalNodes>
      <leafValues>
        -1.7691962420940399e-01 2.4306631088256836e-01</leafValues></_>
    <_>
      <internalNodes>
        0 -1 1122 -304610540 -612449596 -102889502 -211956077
        -1409704303 -1095897362 1380224765 -1703015344</internalNodes>
      <leafValues>
        -1.6783387959003448e-01 2.5707095861434937e-01</leafValues></_>
    <_>
      <internalNodes>
        0 -1 1984 1662599612 1903594045 -1039187563 -796003674
        1027673480 -271545682 1081505933 2021425299</internalNodes>
      <leafValues>
        -2.0491406321525574e-01 2.1572829782962799e-01</leafValues></_>
    <_>
      <internalNodes>
        0 -1 924 -1514263051 -472193743 -229219011 -111897984 -71344899
        -5494379 -1983547991 -668480112</internalNodes>
      <leafValues>
        -1.5294182300567627e-01 2.9554027318954468e-01</leafValues></_>
    <_>
      <internalNodes>
        0 -1 536 335823438 -968579896 614336036 -1539814714 -569882080
        1078486953 1677722901 1087950853</internalNodes>
      <leafValues>
        -4.3767586350440979e-01 1.0451915115118027e-01</leafValues></_>
    <_>
      <internalNodes>
        0 -1 40 1748908952 354195093 -1809674039 -685990533 -1492905264
        -928309752 554601165 1861314416</internalNodes>
      <leafValues>
        -2.7633577585220337e-01 1.5824358165264130e-01</leafValues></_>
    <_>
      <internalNodes>
        0 -1 842 -1038882270 -1077503595 -488142913 -2057974975
        1489668095 -996614358 -1434910500 -1345169410</internalNodes>
      <leafValues>
        -1.6349107027053833e-01 2.6963049173355103e-01</leafValues></_>
    <_>
      <internalNodes>
        0 -1 1445 -757711276 -1210048734 -1574507368 -82772252
        -1368901784 268266599 -1877926152 -441439467</internalNodes>
      <leafValues>
        -2.0618584752082825e-01 2.1528413891792297e-01</leafValues></_></weakClassifiers></stage7>
</opencv_storage>
